rubeus/__init__.py
rubeus/_rubeus_scripts.py
rubeus/py.typed
rubeus/version.py
rubeus/api_resources/__init__.py
rubeus/api_resources/apis.py
rubeus/api_resources/base_client.py
rubeus/api_resources/client.py
rubeus/api_resources/common_types.py
rubeus/api_resources/exceptions.py
rubeus/api_resources/global_constants.py
rubeus/api_resources/streaming.py
rubeus/api_resources/utils.py
rubeus-0.1.26.dist-info/LICENSE
rubeus-0.1.26.dist-info/METADATA
rubeus-0.1.26.dist-info/WHEEL
rubeus-0.1.26.dist-info/entry_points.txt
rubeus-0.1.26.dist-info/top_level.txt
rubeus-0.1.26.dist-info/zip-safe
rubeus-0.1.26.dist-info/RECORD
