Metadata-Version: 2.1
Name: rubeus
Version: 0.1.26
Summary: Python client library for the Rubeus API
Home-page: https://github.com/Portkey-AI/rubeus-python-sdk
Author: Portkey.ai
Author-email: support@portkey.ai
Classifier: Programming Language :: Python :: 3
Classifier: License :: OSI Approved :: MIT License
Classifier: Operating System :: OS Independent
Requires-Python: >=3.8
License-File: LICENSE
Requires-Dist: httpx
Requires-Dist: mypy ==0.991
Requires-Dist: black ==23.7.0
Requires-Dist: typing-extensions ==4.7.1
Requires-Dist: pydantic ==1.10.12
Provides-Extra: dev
Requires-Dist: mypy ==0.991 ; extra == 'dev'
Requires-Dist: black ==23.7.0 ; extra == 'dev'
Requires-Dist: typing-extensions ==4.7.1 ; extra == 'dev'
Requires-Dist: pydantic ==1.10.12 ; extra == 'dev'
